commander_data/__init__.py
commander_data/api.py
commander_data/common.py
commander_data/run.py
commander_data/tests/__init__.py
commander_data/tests/test_common.py
commander_data/tests/test_init.py
commander_data/tests/test_run.py
commander_data-2024.1.19.63931.dist-info/METADATA
commander_data-2024.1.19.63931.dist-info/WHEEL
commander_data-2024.1.19.63931.dist-info/top_level.txt
commander_data-2024.1.19.63931.dist-info/RECORD
